Workbook

Sheet Resumen Ejecutivo
A1: PRESUPUESTO DEL PROYECTO — SGOHA
A2: Sistema de Generación Óptima de Horarios Académicos | Universidad Continental | 2026
A4: INFORMACIÓN GENERAL DEL PROYECTO
A5: Proyecto | B5: SGOHA – Generación Óptima de Horarios Académicos
A6: Equipo | B6: Sanchez Ramos, Giovany / Calderon Aliaga, Kenedy
A7: Metodología | B7: Scrum – Spec-Driven Development (SDD)
A8: Fecha de inicio | B8: 23/03/2026
A9: Fecha de fin estimada | B9: 01/06/2026
A10: Duración total | B10: 10 semanas
A11: Número de Sprints | B11: 5 (Sprint 0 al Sprint 4)
A12: Moneda | B12: Soles peruanos (PEN / S/.)
A14: RESUMEN DE COSTOS POR CATEGORÍA
A15: Categoría | B15: Costo Total (S/.) | C15: % del Presupuesto | D15: Referencia
A16: Recursos Humanos | B16: ='Recursos Humanos'!I2 -> Costo Total (S/.) | C16: =IFERROR(B16/B19,0) -> 0 | D16: Ver hoja RRHH
A17: Infraestructura Tech. | B17: =Infraestructura!D14 -> 0 | C17: =IFERROR(B17/B19,0) -> 0 | D17: Ver hoja Infraestructura
A18: Costos Indirectos | B18: ='Costos Indirectos'!C12 -> 0 | C18: =IFERROR(B18/B19,0) -> 0 | D18: Ver hoja Costos Indirectos
A19: TOTAL PRESUPUESTO | B19: =SUM(B16:B18) -> 0 | C19: =IFERROR(B19/B19,0) -> 0 | D19: Costo total del proyecto

Sheet Recursos Humanos
A1: COSTOS DE RECURSOS HUMANOS
A2: Integrante / Rol | B2: Actividad Principal | C2: Sprint 0 (2 sem) | D2: Sprint 1 (2 sem) | E2: Sprint 2 (3 sem) | F2: Sprint 3 (3 sem) | G2: Sprint 4 (2 sem) | H2: Total Horas | I2: Costo Total (S/.)
A3: Sanchez Ramos, Giovany (Desarrollador Full-Stack / Scrum Master) | B3: Arquitectura, Backend CSP, Coordinación Scrum | C3: 20 | D3: 16 | E3: 30 | F3: 24 | G3: 18 | H3: =SUM(C3:G3) -> 108 | I3: =H3*12 -> 1296
A4: Sanchez Ramos, Giovany (Desarrollador Full-Stack / Scrum Master) | B4: Documentación SDD, Especificaciones, README | C4: 10 | D4: 8 | E4: 6 | F4: 6 | G4: 8 | H4: =SUM(C4:G4) -> 38 | I4: =H4*12 -> 456
A5: Calderon Aliaga, Kenedy (Desarrollador Full-Stack / QA) | B5: Frontend React/TypeScript, Portal Alumno | C5: 8 | D5: 18 | E5: 24 | F5: 30 | G5: 14 | H5: =SUM(C5:G5) -> 94 | I5: =H5*12 -> 1128
A6: Calderon Aliaga, Kenedy (Desarrollador Full-Stack / QA) | B6: Pruebas TDD, Integración, Revisión PR | C6: 8 | D6: 10 | E6: 16 | F6: 14 | G6: 14 | H6: =SUM(C6:G6) -> 62 | I6: =H6*12 -> 744
A7: TOTAL | C7: =SUM(C3:C6) -> 46 | D7: =SUM(D3:D6) -> 52 | E7: =SUM(E3:E6) -> 76 | F7: =SUM(F3:F6) -> 74 | G7: =SUM(G3:G6) -> 54 | H7: =SUM(H3:H6) -> 302 | I7: =SUM(I3:I6) -> 3624
A9: * Tarifa horaria base: S/. 12.00/hora (Desarrollador Junior — mercado Huancayo, 2026)

Sheet Infraestructura
A1: COSTOS DE INFRAESTRUCTURA TECNOLÓGICA
A2: Componente | B2: Tipo | C2: Costo Mensual (S/.) | D2: Meses en Proyecto | E2: Costo Total (S/.)
A3: MongoDB Atlas (M0 Free Tier) | B3: Base de Datos Cloud | C3: 0 | D3: 3 | E3: =C3*D3 -> 0
A4: Vercel (Frontend Deploy) | B4: Hosting Frontend | C4: 0 | D4: 3 | E4: =C4*D4 -> 0
A5: Render.com (Backend Free) | B5: Hosting Backend | C5: 0 | D5: 3 | E5: =C5*D5 -> 0
A6: GitHub (repositorio privado) | B6: Control de versiones | C6: 0 | D6: 3 | E6: =C6*D6 -> 0
A7: VS Code + extensiones | B7: IDE / Herramientas Dev | C7: 0 | D7: 3 | E7: =C7*D7 -> 0
A8: Node.js + npm ecosystem | B8: Runtime / Dependencias | C8: 0 | D8: 3 | E8: =C8*D8 -> 0
A9: Postman (API testing) | B9: Testing herramienta | C9: 0 | D9: 3 | E9: =C9*D9 -> 0
A10: Equipos de cómputo personales (2 laptops, depreciación 3 meses) | B10: Hardware (depreciación) | C10: 60 | D10: 3 | E10: =C10*D10 -> 180
A11: Conexión a Internet (2 usuarios) | B11: Conectividad | C11: 50 | D11: 3 | E11: =C11*D11 -> 150
A12: Electricidad estimada (2 equipos) | B12: Servicios básicos | C12: 20 | D12: 3 | E12: =C12*D12 -> 60
A13: Licencia Windows / herramientas (proporcional al proyecto) | B13: Licencias | C13: 10 | D13: 3 | E13: =C13*D13 -> 30
A14: TOTAL INFRAESTRUCTURA | E14: =SUM(E3:E13) -> 420
A16: * Herramientas con costo S/. 0.00 utilizan planes gratuitos disponibles al momento del proyecto.

Sheet Costos Indirectos
A1: COSTOS INDIRECTOS DEL PROYECTO
A2: Concepto | B2: Descripción | C2: Frecuencia / Base | D2: Costo Estimado (S/.)
A3: Transporte y reuniones de equipo | B3: Movilidad para coordinación presencial entre integrantes | C3: 2 veces/semana × 10 sem × S/. 3 | D3: 60
A4: Impresión de documentación | B4: Impresión de entregables, rúbricas y especificaciones | C4: Estimado global del proyecto | D4: 30
A5: Capacitación / cursos en línea | B5: Tutoriales, documentación técnica de algoritmos CSP | C5: Recursos gratuitos + subscripción puntual | D5: 0
A6: Margen de contingencia (10%) | B6: Reserva para imprevistos y ajustes de alcance | C6: 10% sobre RRHH + Infraestructura | D6: =('Recursos Humanos'!I6+Infraestructura!E14)*0.1 -> 116.4
A7: Tiempo de coordinación no productiva | B7: Reuniones de seguimiento, dailys, retrospectivas Scrum | C7: Valorizado a S/. 12/h × 20h totales estimadas | D7: 240
A8: Costo de presentación final | B8: Materiales para exposición, demo en vivo, diapositivas | C8: Estimado global | D8: 50
A9: Overhead académico | B9: Tiempo dedicado a documentación universitaria obligatoria | C9: Valorizado a S/. 10/h × 15h estimadas | D9: 150
A10: TOTAL COSTOS INDIRECTOS | D10: =SUM(D3:D9) -> 646.4

Sheet Costo por Sprint
A1: EVOLUCIÓN DE COSTOS POR SPRINT
A2: Sprint | B2: Período | C2: Costo RRHH (S/.) | D2: Costo Infra (S/.) | E2: Costo Indirecto (S/.) | F2: Costo Sprint (S/.) | G2: Costo Acumulado (S/.)
A3: Sprint 0 | B3: 23/03 – 05/04/2026 | C3: =SUM('Recursos Humanos'!C3:C6)*12 -> 552 | D3: 30 | E3: 30 | F3: =C3+D3+E3 -> 612 | G3: =F3 -> 612
A4: Sprint 1 | B4: 06/04 – 19/04/2026 | C4: =SUM('Recursos Humanos'!D3:D6)*12 -> 624 | D4: 30 | E4: 30 | F4: =C4+D4+E4 -> 684 | G4: =G3+F4 -> 1296
A5: Sprint 2 | B5: 20/04 – 10/05/2026 | C5: =SUM('Recursos Humanos'!E3:E6)*12 -> 912 | D5: 50 | E5: 40 | F5: =C5+D5+E5 -> 1002 | G5: =G4+F5 -> 2298
A6: Sprint 3 | B6: 11/05 – 31/05/2026 | C6: =SUM('Recursos Humanos'!F3:F6)*12 -> 888 | D6: 40 | E6: 40 | F6: =C6+D6+E6 -> 968 | G6: =G5+F6 -> 3266
A7: Sprint 4 | B7: 01/06/2026 | C7: =SUM('Recursos Humanos'!G3:G6)*12 -> 648 | D7: 20 | E7: 20 | F7: =C7+D7+E7 -> 688 | G7: =G6+F7 -> 3954
A8: TOTAL | C8: =SUM(C3:C7) -> 3624 | D8: =SUM(D3:D7) -> 170 | E8: =SUM(E3:E7) -> 160 | F8: =SUM(F3:F7) -> 3954 | G8: =G7 -> 3954

Sheet Green Software
A1: ANÁLISIS DE SOSTENIBILIDAD — GREEN SOFTWARE
A2: Evaluación del impacto ambiental y estrategias de eficiencia energética del SGOHA
A3: Principio Green Software | B3: Estrategia Aplicada en SGOHA | C3: Estado | D3: Impacto Estimado
A4: Eficiencia energética (Energy Efficiency) | B4: Uso de MongoDB Atlas Free Tier y Vercel/Render gratuitos: servidores compartidos optimizan consumo vs. servidor dedicado propio. | C4: ✅ Implementado | D4: Reducción ~70% consumo vs. servidor físico propio
A5: Hardware eficiente (Hardware Efficiency) | B5: El algoritmo CSP con AC-3 reduce el espacio de búsqueda antes del backtracking, minimizando ciclos de CPU y tiempo de cómputo. | C5: ✅ Implementado | D5: Reducción del espacio de búsqueda hasta 60% con AC-3
A6: Demanda ajustable (Carbon Awareness) | B6: El proceso de generación de horarios se ejecuta bajo demanda explícita del administrador, no en background continuo. | C6: ✅ Implementado | D6: Sin consumo base innecesario en servidor
A7: Medición de rendimiento (Measurement) | B7: El sistema reporta tiempo de ejecución del algoritmo CSP (executionTimeMs) y número de backtrackings, permitiendo optimizar iteraciones. | C7: ✅ Implementado | D7: Visibilidad de eficiencia computacional por generación
A8: Minimizar transferencia de datos (Network Efficiency) | B8: La API REST retorna solo los campos necesarios por endpoint. El frontend usa Zustand para cachear estado y evitar peticiones redundantes. | C8: ✅ Implementado | D8: Reducción de payload estimada en 40%
A9: Escalabilidad sostenible (Scalability) | B9: Arquitectura MERN permite escalar horizontalmente solo cuando la demanda lo requiera, sin sobredimensionar desde el inicio. | C9: 🔄 Planificado | D9: Evita costos de sobre-aprovisionamiento
A10: Código limpio y mantenible (Software Quality) | B10: Pruebas TDD con cobertura >70% reducen bugs, evitando ciclos de depuración costosos en energía y tiempo de desarrollo. | C10: ✅ Implementado | D10: Menor deuda técnica = menor energía a largo plazo
A12: Conclusión: El SGOHA adopta prácticas Green Software en su etapa de desarrollo académico mediante el uso de infraestructura gratuita de bajo consumo, algoritmos computacionalmente eficientes (AC-3 + MRV + LCV), ejecución bajo demanda y código de alta cobertura que reduce retrabajo energético. El costo ambiental del proyecto es mínimo comparado con sistemas equivalentes sobre infraestructura física dedicada.
